gerrit_to_github_issues/__init__.py
gerrit_to_github_issues/cli.py
gerrit_to_github_issues/engine.py
gerrit_to_github_issues/errors.py
gerrit_to_github_issues/gerrit.py
gerrit_to_github_issues/github_issues.py
gerrit_to_github_issues-0.0.4.dist-info/AUTHORS
gerrit_to_github_issues-0.0.4.dist-info/LICENSE
gerrit_to_github_issues-0.0.4.dist-info/METADATA
gerrit_to_github_issues-0.0.4.dist-info/WHEEL
gerrit_to_github_issues-0.0.4.dist-info/entry_points.txt
gerrit_to_github_issues-0.0.4.dist-info/pbr.json
gerrit_to_github_issues-0.0.4.dist-info/top_level.txt
gerrit_to_github_issues-0.0.4.dist-info/RECORD
